aioprocessing/__init__.py
aioprocessing/connection.py
aioprocessing/executor.py
aioprocessing/locks.py
aioprocessing/managers.py
aioprocessing/mp.py
aioprocessing/pool.py
aioprocessing/process.py
aioprocessing/queues.py
aioprocessing/util.py
aioprocessing-2.0.0.dist-info/AUTHORS
aioprocessing-2.0.0.dist-info/LICENSE.txt
aioprocessing-2.0.0.dist-info/METADATA
aioprocessing-2.0.0.dist-info/WHEEL
aioprocessing-2.0.0.dist-info/top_level.txt
aioprocessing-2.0.0.dist-info/RECORD
