Metadata-Version: 2.1
Name: aioprocessing
Version: 2.0.0
Summary: A Python 3.5+ library that integrates the multiprocessing module with asyncio.
Home-page: https://github.com/dano/aioprocessing
Author: Dan O'Reilly
Author-email: oreilldf@gmail.com
License: BSD
Keywords: asyncio multiprocessing coroutine
Platform: UNKNOWN
Classifier: Development Status :: 3 - Alpha
Classifier: Intended Audience :: Developers
Classifier: Natural Language :: English
Classifier: License :: OSI Approved :: BSD License
Classifier: Operating System :: Microsoft :: Windows
Classifier: Operating System :: POSIX
Classifier: Programming Language :: Python :: Implementation :: CPython
Classifier: Programming Language :: Python
Classifier: Programming Language :: Python :: 3
Classifier: Programming Language :: Python :: 3.5
Classifier: Programming Language :: Python :: 3.6
Classifier: Programming Language :: Python :: 3.7
Classifier: Programming Language :: Python :: 3.8
Classifier: Programming Language :: Python :: 3.9
Classifier: Programming Language :: Python :: 3.10
Classifier: Topic :: Software Development :: Libraries :: Python Modules
Provides-Extra: dill
Requires-Dist: multiprocess ; extra == 'dill'
